kvalchemy/__init__.py
kvalchemy/client.py
kvalchemy/models.py
kvalchemy/proxy.py
kvalchemy/time.py
kvalchemy/values.py
kvalchemy-0.2.3.dist-info/LICENSE.md
kvalchemy-0.2.3.dist-info/METADATA
kvalchemy-0.2.3.dist-info/WHEEL
kvalchemy-0.2.3.dist-info/top_level.txt
kvalchemy-0.2.3.dist-info/RECORD
