Metadata-Version: 2.1
Name: kvalchemy
Version: 0.2.3
Summary: A SQLAlchemy based Key-Value store.
Author-email: csm10495 <csm10495@gmail.com>
License: MIT License
Project-URL: homepage, https://github.com/csm10495/kvalchemy
Project-URL: repository, https://github.com/csm10495/kvalchemy
Project-URL: documentation, https://csm10495.github.io/kvalchemy
Classifier: Intended Audience :: Developers
Classifier: Natural Language :: English
Classifier: Operating System :: POSIX
Classifier: Operating System :: Microsoft :: Windows
Classifier: Programming Language :: Python
Classifier: Programming Language :: Python :: 3
Requires-Python: >=3.8
License-File: LICENSE.md
Requires-Dist: backoff
Requires-Dist: sqlalchemy
Provides-Extra: dev
Requires-Dist: func-timeout ; extra == 'dev'
Requires-Dist: oracledb ; extra == 'dev'
Requires-Dist: psycopg2-binary ; extra == 'dev'
Requires-Dist: PyMySQL[rsa] ; extra == 'dev'
Requires-Dist: pytest ; extra == 'dev'
Requires-Dist: pymssql ; (platform_system != "Darwin") and extra == 'dev'
